STmulator/__init__.py
STmulator/STmulator_core/__init__.py
STmulator/STmulator_core/simulator.py
STmulator/STmulator_core/simulator_3D_ref.py
STmulator/interpolation/__init__.py
STmulator/interpolation/interpolation_gene_expression.py
STmulator/interpolation/interpolation_pipe.py
STmulator/interpolation/interpolation_spatial.py
STmulator/modeling/__init__.py
STmulator/modeling/simulator_fit.py
STmulator/modeling/simulator_generation.py
STmulator/optimization/__init__.py
STmulator/optimization/ot_optimization.py
STmulator/variable/__init__.py
STmulator/variable/threed_val_cal.py
STmulator/variable/var_cal.py
STmulator/variable/var_distribution.py
STmulator/variable/var_evaluation.py
STmulator/variable/var_model_fit.py
STmulator/variable/var_preprocess.py
STmulator/variable/var_sim_helper.py
STmulator/variable/variable_process.py
STmulator-0.1.4.dist-info/LICENSE
STmulator-0.1.4.dist-info/METADATA
STmulator-0.1.4.dist-info/WHEEL
STmulator-0.1.4.dist-info/top_level.txt
STmulator-0.1.4.dist-info/RECORD
