Metadata-Version: 2.1
Name: STmulator
Version: 0.1.4
Summary: 3D Spatial Transcriptomics Simulator, with realistic varaince modeling and statiscial fitting. Here is a early preview version.
Author-email: Yiru CHEN <yiru.22@intl.zju.edu.cn>
License: MIT
Project-URL: Homepage, https://github.com/maiziezhoulab/SimulaTor
Project-URL: Repository, https://github.com/maiziezhoulab/SimulaTor
Classifier: Programming Language :: Python :: 3
Classifier: License :: OSI Approved :: MIT License
Classifier: Operating System :: OS Independent
Requires-Python: >=3.8
License-File: LICENSE
Requires-Dist: alphashape>=1.3.1
Requires-Dist: anndata>=0.9.2
Requires-Dist: geomloss>=0.2.6
Requires-Dist: joblib>=1.4.2
Requires-Dist: matplotlib>=3.7.5
Requires-Dist: numba>=0.55.2
Requires-Dist: numpy>=1.22.4
Requires-Dist: pandas>=2.0.3
Requires-Dist: paste2>=1.0.1
Requires-Dist: scanpy>=1.9.8
Requires-Dist: scikit-learn>=1.2.1
Requires-Dist: scipy>=1.10.1
Requires-Dist: seaborn>=0.13.2
Requires-Dist: torch>=1.12.1
Requires-Dist: tqdm>=4.66.4
